README.md
setup.py
onnawsorgs/__init__.py
onnawsorgs/orgs.py
onnawsorgs.egg-info/PKG-INFO
onnawsorgs.egg-info/SOURCES.txt
onnawsorgs.egg-info/dependency_links.txt
onnawsorgs.egg-info/requires.txt
onnawsorgs.egg-info/top_level.txt