Metadata-Version: 2.1
Name: onnawsorgs
Version: 0.0.5
Summary: Convenience Python module for AWS Organisations & STS
Home-page: https://onnawsorgs.oznetnerd.com
Author: Will Robinson
Author-email: will@oznetnerd.com
License: UNKNOWN
Platform: UNKNOWN
